dummy_lib_example/__init__.py
dummy_lib_example/core.py
dummy_lib_example-0.1.0.dist-info/licenses/LICENSE
dummy_lib_example-0.1.0.dist-info/METADATA
dummy_lib_example-0.1.0.dist-info/WHEEL
dummy_lib_example-0.1.0.dist-info/top_level.txt
dummy_lib_example-0.1.0.dist-info/RECORD
