Metadata-Version: 2.4
Name: dummy-lib-example
Version: 0.1.0
Summary: A dummy Python library for demonstration purposes
Author-email: Soham Pal <youremail@example.com>
License: MIT
Keywords: dummy,example,demo
Classifier: Programming Language :: Python :: 3
Classifier: License :: OSI Approved :: MIT License
Classifier: Operating System :: OS Independent
Requires-Python: >=3.7
License-File: LICENSE
Dynamic: license-file
